[
    {
  "name": "Pawa",
  "username": "Pawa",
  "datePost": "Dec 15 2025 9:40PM",
  "content": "Cat is on Duty",
  "iframe": "",
  "video": "https://i.imgur.com/MTvD2XI.mp4",
  "image": "",
  "likes": 864,
  "liked": false,
  "topic": "Viral"
},
{
  "name": "Relights",
  "username": "Relights",
  "datePost": "Dec 15 2025 9:39PM",
  "content": "Hey, Baby",
  "iframe": "",
  "video": "https://i.imgur.com/RUGVyFy.mp4",
  "image": "",
  "likes": 83491,
  "liked": false,
  "topic": "Random"
},
{
  "name": "Femination",
  "username": "Femination",
  "datePost": "Dec 15 2025 9:38PM",
  "content": "Mermaid Monday",
  "iframe": "",
  "video": "",
  "image": "https://i.imgur.com/PDUE7De_d.webp?maxwidth=520&amp;shape=thumb&amp;fidelity=high",
  "likes": 8649,
  "liked": false,
  "topic": "Viral"
},
{
  "name": "DropDrop",
  "username": "DropDrop",
  "datePost": "Dec 15 2025 9:37PM",
  "content": "",
  "iframe": "",
  "video": "https://i.imgur.com/6ZYVyMI.mp4",
  "image": "",
  "likes": 226,
  "liked": false,
  "topic": ""
},
{
  "name": "DropDrop",
  "username": "DropDrop",
  "datePost": "Dec 15 2025 9:36PM",
  "content": "9 hours and 18 minutes for the theatrical cuts or 11 hours and 23 minutes for the extended editions..",
  "iframe": "",
  "video": "https://i.imgur.com/gLsTLsJ.mp4",
  "image": "",
  "likes": 8546,
  "liked": false,
  "topic": "Funny"
},
{
  "name": "prosicate",
  "username": "prosicate",
  "datePost": "Dec 15 2025 9:35PM",
  "content": "",
  "iframe": "",
  "video": "https://i.imgur.com/RiOEnMO.mp4",
  "image": "",
  "likes": 764,
  "liked": false,
  "topic": ""
},
{
  "name": "prosicate",
  "username": "prosicate",
  "datePost": "Dec 15 2025 9:35PM",
  "content": "When you hire civil servants, give them a large chunk of your paycheck and then still have to do the work yourself.",
  "iframe": "",
  "video": "https://i.imgur.com/soGpJRo.mp4",
  "image": "",
  "likes": 79431,
  "liked": false,
  "topic": "Random"
},
{
  "name": "Duke",
  "username": "Duke",
  "datePost": "Dec 15 2025 9:33PM",
  "content": "A.I Litteraly",
  "iframe": "",
  "video": "https://i.imgur.com/PqUTO74.mp4",
  "image": "",
  "likes": 8246,
  "liked": false,
  "topic": "A.I"
},
{
  "name": "DropDrop",
  "username": "DropDrop",
  "datePost": "Dec 15 2025 9:32PM",
  "content": "Is legal to support genocide..",
  "iframe": "",
  "video": "https://i.imgur.com/WJOqIRk.mp4",
  "image": "",
  "likes": 8343,
  "liked": false,
  "topic": "Protest"
},
{
  "name": "THEGOAT🔥🐐",
  "username": "THEGOAT",
  "datePost": "Dec 15 2025 9:27PM",
  "content": "",
  "iframe": "",
  "video": "https://deenzedblogstaticserver.wordpress.com/wp-content/uploads/2025/12/wp-1765803439466.mp4",
  "image": "",
  "likes": 976464,
  "liked": false,
  "topic": "Trending"
},
{
  "name": "Akositomboy",
  "username": "Akositomboy",
  "datePost": "Dec 15 2025 9:27PM",
  "content": "",
  "iframe": "",
  "video": "https://deenzedblogstaticserver.wordpress.com/wp-content/uploads/2025/12/wp-1765803445275.mp4",
  "image": "",
  "likes": 465,
  "liked": false,
  "topic": "Movie"
},
{
  "name": "DxmK",
  "username": "DxmK",
  "datePost": "Dec 15 2025 9:26PM",
  "content": "",
  "iframe": "",
  "video": "https://deenzedblogstaticserver.wordpress.com/wp-content/uploads/2025/12/wp-1765803443102.mp4",
  "image": "",
  "likes": 4976,
  "liked": false,
  "topic": "Viral"
},
{
  "name": "Akositomboy",
  "username": "Akositomboy",
  "datePost": "Dec 15 2025 9:26PM",
  "content": "Oh",
  "iframe": "",
  "video": "https://deenzedblogstaticserver.wordpress.com/wp-content/uploads/2025/12/wp-1765803444210.mp4",
  "image": "",
  "likes": 1946,
  "liked": false,
  "topic": "Movie"
},
{
  "name": "Inn ital",
  "username": "Inntail",
  "datePost": "Dec 15 2025 9:24PM",
  "content": "Radiohead",
  "iframe": "",
  "video": "https://deenzedblogstaticserver.wordpress.com/wp-content/uploads/2025/12/wp-1765803445617.mp4",
  "image": "",
  "likes": 4543,
  "liked": false,
  "topic": "Trend"
},
{
  "name": "tae",
  "username": "taeOriginal",
  "datePost": "Dec 15 2025 9:23PM",
  "content": "This is real",
  "iframe": "",
  "video": "https://deenzedblogstaticserver.wordpress.com/wp-content/uploads/2025/12/wp-1765803446422.mp4",
  "image": "",
  "likes": 7643,
  "liked": false,
  "topic": "Trending"
},
{
  "name": "tae",
  "username": "taeOriginal",
  "datePost": "Dec 15 2025 9:22PM",
  "content": "Like fr",
  "iframe": "",
  "video": "https://deenzedblogstaticserver.wordpress.com/wp-content/uploads/2025/12/wp-1765803446593.mp4",
  "image": "",
  "likes": 86494,
  "liked": false,
  "topic": "Entertaining"
},
{
  "name": "Airsoft",
  "username": "Airsoft",
  "datePost": "Dec 15 2025 9:22PM",
  "content": "More Crazy is ts is just airsoft",
  "iframe": "",
  "video": "https://deenzedblogstaticserver.wordpress.com/wp-content/uploads/2025/12/wp-1765803440963.mp4",
  "image": "",
  "likes": 58623,
  "liked": false,
  "topic": "Viral"
},
{
  "name": "Uok",
  "username": "Uok",
  "datePost": "Dec 15 2025 9:21PM",
  "content": "He got tackel",
  "iframe": "",
  "video": "https://deenzedblogstaticserver.wordpress.com/wp-content/uploads/2025/12/wp-1765803446902.mp4",
  "image": "",
  "likes": 74648,
  "liked": false,
  "topic": "News"
},
  {
  "name": "THEGOAT🔥🐐",
  "username": "THEGOAT",
  "datePost": "Dec 15 2025 8:54PM",
  "content": "GROK THE REAL ONE 🔥🐐",
  "iframe": "",
  "video": "https://deenzedblogstaticserver.wordpress.com/wp-content/uploads/2025/12/savetik.co_7583740807279037710.mp4",
  "image": "",
  "likes": 999941,
  "liked": false,
  "topic": "Edit"
},
{
  "name": "Chei Uabn Fhsu Haos",
  "username": "Chei Uabn Fhsu Haos",
  "datePost": "Dec 15 2025 8:53PM",
  "content": "Shachi",
  "iframe": "",
  "video": "https://deenzedblogstaticserver.wordpress.com/wp-content/uploads/2025/12/burjkhalifa_touchintheskysincedayone23dubaiwonder23exploredubai23historyinthemaking23viralshorts.mp4",
  "image": "",
  "likes": 8645,
  "liked": false,
  "topic": "Viral"
},
{
  "name": "THEGOAT🔥🐐",
  "username": "THEGOAT",
  "datePost": "Dec 15 2025 8:46PM",
  "content": "",
  "iframe": "",
  "video": "https://deenzedblogstaticserver.wordpress.com/wp-content/uploads/2025/04/savetik.co_7434625274240585002.mp4",
  "image": "",
  "likes": 99460,
  "liked": false,
  "topic": "Edit"
},
{
  "name": "Ufosj",
  "username": "Ufosj",
  "datePost": "Dec 15 2025 8:45PM",
  "content": "Kabataan nag away parang mga aso",
  "iframe": "",
  "video": "https://deenzedblogstaticserver.wordpress.com/wp-content/uploads/2025/04/aqpq3kcjc5cgae4i9tm48i08t-nutsv09nqofc98ulnakudo3t9zoj7vgffvm9fxurinsaayvhs8_hnkugpu6rnf.mp4",
  "image": "",
  "likes": 241,
  "liked": false,
  "topic": "Away"
},
{
  "name": "User384828",
  "username": "User384828",
  "datePost": "Dec 15 2025 8:44PM",
  "content": "",
  "iframe": "",
  "video": "https://deenzedblogstaticserver.wordpress.com/wp-content/uploads/2025/04/2025-04-15-223726846.mp4",
  "image": "",
  "likes": 5313,
  "liked": false,
  "topic": "Cat"
},
{
  "name": "Groxfan",
  "username": "Groxfan",
  "datePost": "Dec 15 2025 8:38PM",
  "content": "Doggo🥀",
  "iframe": "",
  "video": "https://deenzedblogstaticserver.wordpress.com/wp-content/uploads/2025/04/myminecraftdogpassedaway_28.mp4",
  "image": "",
  "likes": 424349,
  "liked": false,
  "topic": "Minecraft"
},
{
  "name": "Pets",
  "username": "Pets",
  "datePost": "Dec 15 2025 8:37PM",
  "content": "Angry",
  "iframe": "",
  "video": "https://deenzedblogstaticserver.wordpress.com/wp-content/uploads/2025/04/snapsave.app_-71o7httmi1rgh4bnp9qwvq32nc.mp4",
  "image": "",
  "likes": 2365,
  "liked": false,
  "topic": "Puppy"
},
{
  "name": "TaeOriginal",
  "username": "TaeOriginal",
  "datePost": "Dec 15 2025 8:37PM",
  "content": "Gira ra mo kaon ra ko",
  "iframe": "",
  "video": "https://deenzedblogstaticserver.wordpress.com/wp-content/uploads/2025/04/snapsave.app_-vbcj02jp5re9q24vpgj8rlavtjytywxbhwsct7ls6428rqli2sihpd1tlxoumkljjxpbcfh.mp4",
  "image": "",
  "likes": 86417,
  "liked": false,
  "topic": "Viral"
},
{
  "name": "Zezzy",
  "username": "Zezzy",
  "datePost": "Dec 15 2025 8:36PM",
  "content": "DANGGGG",
  "iframe": "",
  "video": "https://deenzedblogstaticserver.wordpress.com/wp-content/uploads/2025/04/saveclip.app_aqmoboajggpyvswgvzlmsq94l2rslupzvgm5hztzxogcxz92khd4e_zdqwev5vhglj0espgcr-8c-z4p9eqziv4ktu9wzpgepfk6dyi.mp4",
  "image": "",
  "likes": 83495,
  "liked": false,
  "topic": "Viral"
},
{
  "name": "ViolencePage",
  "username": "ViolencePage",
  "datePost": "Dec 15 2025 8:35PM",
  "content": "Mud trimming😭",
  "iframe": "",
  "video": "https://deenzedblogstaticserver.wordpress.com/wp-content/uploads/2025/04/saveclip.app_aqo9shnzfhzlgcq-xhxvp4pqv6uyii9mgvxwftw5qwx0fdangwdcwzk5bzsynsptb_g-29wgcpto_1potea_gmramgr7woxxovaw6q4.mp4",
  "image": "",
  "likes": 1056,
  "liked": false,
  "topic": "Viral"
},
{
  "name": "ViolencePage",
  "username": "ViolencePage",
  "datePost": "Dec 15 2025 8:34PM",
  "content": "Hood🥀",
  "iframe": "",
  "video": "https://deenzedblogstaticserver.wordpress.com/wp-content/uploads/2025/04/saveclip.app_aqoarnmwgxihkbfo_t-vrjbqdhunpwy0v3pbbevfbzcrjozhokh9avfc0sd5td20mf2itueju3qvjgcgyi2ovp09ts0k64asmsddeta.mp4",
  "image": "",
  "likes": 7649,
  "liked": false,
  "topic": "Viral"
},
{
  "name": "ViolencePage",
  "username": "ViolencePage",
  "datePost": "Dec 15 2025 8:34PM",
  "content": "",
  "iframe": "",
  "video": "https://deenzedblogstaticserver.wordpress.com/wp-content/uploads/2025/04/saveclip.app_aqmleftsmarq8rnem54upsifkxw1afezwltxk82h_3tbftw2tuz8odsspnwqsjyqyc7u-cvjvf45w2afv4v9zqemztuj0mswnvjlbky.mp4",
  "image": "",
  "likes": 85463,
  "liked": false,
  "topic": "Viral"
},
{
  "name": "Relights",
  "username": "Relights",
  "datePost": "Dec 15 2025 8:33PM",
  "content": "Damn...",
  "iframe": "",
  "video": "https://deenzedblogstaticserver.wordpress.com/wp-content/uploads/2025/04/saveclip.app_aqnxe0p55b1kqpkjq63nxgx3_dlpcbi7qxwvnxt_3jr_7oun65s_rwc6pudgtfevh0d0ckf94fgdj3znvh0emnc4dl0l3j9moj2kdqy.mp4",
  "image": "",
  "likes": 24319,
  "liked": false,
  "topic": "Viral"
},
{
  "name": "Deenzed",
  "username": "Deenzed",
  "datePost": "Dec 15 2025 8:32PM",
  "content": "",
  "iframe": "",
  "video": "https://deenzedblogstaticserver.wordpress.com/wp-content/uploads/2025/04/saveclip.app_aqnjavndkmfgwrp-3r48qcotphvtwm9-qi56amlobufg3gdvpvuvdz3aoogl-tm2ew0eficfvc3_dkra2lcbentsgxuyutp7s34z7ke.mp4",
  "image": "",
  "likes": 2436,
  "liked": false,
  "topic": "Viral"
},
{
  "name": "Duke",
  "username": "Duke",
  "datePost": "Dec 15 2025 8:32PM",
  "content": "Thingysss",
  "iframe": "",
  "video": "https://deenzedblogstaticserver.wordpress.com/wp-content/uploads/2025/04/saveclip.app_aqpzjkwwhpouokevo5vupqca-ce2cyezo3fvmwtaa4zmxiifaeaigfif9gkcjxunutnuxhlw6yz6quxqsegljw_usiqanxrtba24dky.mp4",
  "image": "",
  "likes": 8646,
  "liked": false,
  "topic": "Viral"
},
{
  "name": "Duke",
  "username": "Duke",
  "datePost": "Dec 15 2025 8:31PM",
  "content": "Fighting to Carshow then shooting😭",
  "iframe": "",
  "video": "https://deenzedblogstaticserver.wordpress.com/wp-content/uploads/2025/04/saveclip.app_aqozxvcnfjnorcdszy8teawg_v_ojlag6mm4bomfkg3oqcmvgcqgv03ypa_keqtkou_lvx9pdeaymjcv76tgoqhygr5f4rzcobkloby.mp4",
  "image": "",
  "likes": 7343,
  "liked": false,
  "topic": "Viral"
},
{
  "name": "DxmK",
  "username": "DxmK",
  "datePost": "Dec 15 2025 8:30PM",
  "content": "The Switch up😭",
  "iframe": "",
  "video": "https://deenzedblogstaticserver.wordpress.com/wp-content/uploads/2025/04/saveclip.app_aqmloep6amuqxte0bas6qatip0cijj18xqqyngwtta_kxtnc883k5o8qddj2ycoyxu0rqrlcbdh4og7go4l4f0m1d7l1t_tljvqeyya.mp4",
  "image": "",
  "likes": 7246,
  "liked": false,
  "topic": "Viral"
},
{
  "name": "ViolencePage",
  "username": "ViolencePage",
  "datePost": "Dec 15 2025 8:30PM",
  "content": "Cartels",
  "iframe": "",
  "video": "https://deenzedblogstaticserver.wordpress.com/wp-content/uploads/2025/04/saveclip.app_aqp-nm5uqmp1c71jiaubos4396harn28ddnqpaf6puxrkwnoor2lehiy7jsipsmdq8s8j6qajiogvoztvx6fdzpby__j92q39pzaxy0.mp4",
  "image": "",
  "likes": 1349,
  "liked": false,
  "topic": "Viral"
},
{
  "name": "ViolencePage",
  "username": "ViolencePage",
  "datePost": "Dec 15 2025 8:29PM",
  "content": "",
  "iframe": "",
  "video": "https://deenzedblogstaticserver.wordpress.com/wp-content/uploads/2025/04/saveclip.app_aqnub3vqib9drap4evrifnrrry4nmultjm3uxmzdkdkah5z3smkqukq1xejajmq9kdhggasndjpg3ccypwfs08v3jnaolw4ejat9sc4.mp4",
  "image": "",
  "likes": 2434,
  "liked": false,
  "topic": "Viral"
},
{
  "name": "ViolencePage",
  "username": "ViolencePage",
  "datePost": "Dec 15 2025 8:28PM",
  "content": "Like for more content, and Goal to 1M Likes",
  "iframe": "",
  "video": "https://deenzedblogstaticserver.wordpress.com/wp-content/uploads/2025/04/saveclip.app_aqpqavv96afdfypjvag6tkwmsipug_2_jtyrfqdspzks59e-i_mqavrkynz5j904chil-n150dtmzujailenaem4d-hb90xlre1hgvg.mp4",
  "image": "",
  "likes": 82431,
  "liked": false,
  "topic": "Violence"
},
{
  "name": "Airsoft",
  "username": "Airsoft",
  "datePost": "Dec 15 2025 8:27PM",
  "content": "",
  "iframe": "",
  "video": "https://deenzedblogstaticserver.wordpress.com/wp-content/uploads/2025/04/saveclip.app_aqnund4rc4of2x8h9qq-0lszdohriamqnwovz9kr8owrk9mtzuwmcnr2xyzxtfd8v0c1fexnvncle5xrcghaxwvqtdd6nm1uqzxkfoo.mp4",
  "image": "",
  "likes": 89465,
  "liked": false,
  "topic": "Airsoft"
},
{
  "name": "Uok",
  "username": "Uok",
  "datePost": "Dec 15 2025 8:26PM",
  "content": "When fireworks became bombs",
  "iframe": "",
  "video": "https://deenzedblogstaticserver.wordpress.com/wp-content/uploads/2025/04/saveclip.app_aqp_a3erm88wj4kqwg3y3lrbwrob1ibhsxfcmhle9koyhfmok3ln9qjnvyfvyis5lh9dlni2y4201b6ph9mikadng8wyng8w0kswtym.mp4",
  "image": "",
  "likes": 1004,
  "liked": false,
  "topic": "Fireworks"
},
{
  "name": "Fkd",
  "username": "Fkd",
  "datePost": "Dec 15 2025 8:25PM",
  "content": "He came prepared",
  "iframe": "",
  "video": "https://deenzedblogstaticserver.wordpress.com/wp-content/uploads/2025/04/saveclip.app_aqpfnwtszse_x4toivklmnxk2y2kmo6ilrsjwr0jlnzyvxcnw403yzaqiq_1mhtcsejkw-xao0svnmjojawkzfelr-26pj9vfhj13fk.mp4",
  "image": "",
  "likes": 8464,
  "liked": false,
  "topic": "Viral"
},
{
  "name": "Relights",
  "username": "Relights",
  "datePost": "Dec 15 2025 8:24PM",
  "content": "Oh Gosh😳",
  "iframe": "",
  "video": "https://deenzedblogstaticserver.wordpress.com/wp-content/uploads/2025/04/saveclip.app_aqmkpp-pnbn4jrvycivpd5ntg8xj2pl2cqjvvmrjuaj6jhkvidbfo50ic3qnd5xhvi9hg3fs6jk0188t8eprxlflmfujsi7voddcunw.mp4",
  "image": "",
  "likes": 864835,
  "liked": false,
  "topic": "Viral"
},
{
  "name": "ViolencePage",
  "username": "RealMe",
  "datePost": "Dec 15 2025 8:23PM",
  "content": "",
  "iframe": "",
  "video": "https://deenzedblogstaticserver.wordpress.com/wp-content/uploads/2025/04/saveclip.app_aqmfzw_udeog6amg3husbzw2zogqhgxrmprthhyifpzcx8uddnfc2edigb5_o5jtmrw1yua8qq1iwahv98ijkdaqxmmizgqy-dvk97e.mp4",
  "image": "",
  "likes": 2434,
  "liked": false,
  "topic": "Violence"
},
{
  "name": "ViolencePage",
  "username": "RealMe",
  "datePost": "Dec 15 2025 8:23PM",
  "content": "",
  "iframe": "",
  "video": "https://deenzedblogstaticserver.wordpress.com/wp-content/uploads/2025/04/saveclip.app_aqoda3nkwosqoh6o4n6g1etvuny6ejxfyxaz1oqqddt1n7ygdy4llqpmmbtzv7k1f6ncugrdq5xhh3drtetwdmdcpu9abl_rb5hhmpw.mp4",
  "image": "",
  "likes": 8349,
  "liked": false,
  "topic": "Violence"
},
{
  "name": "RealMe",
  "username": "RealMe",
  "datePost": "Dec 15 2025 8:22PM",
  "content": "GT",
  "iframe": "",
  "video": "https://deenzedblogstaticserver.wordpress.com/wp-content/uploads/2025/04/aqmthhujbbzed8ekkjmfdhwimpsffitysyzeuuzz86xf6ksbgxwal7duuwv6lnmlc1c8kevqq-kehngiay1i0whl.mp4",
  "image": "",
  "likes": 2436,
  "liked": false,
  "topic": "Trending"
},
{
  "name": "Essko",
  "username": "Essko",
  "datePost": "Dec 15 2025 8:20PM",
  "content": "Tulis",
  "iframe": "",
  "video": "https://deenzedblogstaticserver.wordpress.com/wp-content/uploads/2025/06/aqoy2eenkx3dvlpnbbnfunbe6mccz7tclq-oqsudv-cyyeqm9pk8akmn4zqjuo0ht9dmhui05fikaz6tezjlwt57.mp4",
  "image": "",
  "likes": 9053,
  "liked": false,
  "topic": "Trending"
},

    
    
    {
      "name": "MusicHeart",
      "username": "MusicHeart",
      "datePost": "Dec 13 2025 7:50PM",
      "content": "Girlfriends - New Computers",
      "iframe": "https://www.youtube.com/embed/-VzyB87A08U",
      "video": "",
      "image": "",
      "likes": 732781,
      "liked": false,
      "topic": "Music"
    },
    {
      "name": "MusicHeart",
      "username": "MusicHeart",
      "datePost": "Dec 13 2025 7:49PM",
      "content": "No Suprises - Radiohead",
      "iframe": "https://www.youtube.com/embed/LBt60dfwEBY",
      "video": "",
      "image": "",
      "likes": 834659,
      "liked": false,
      "topic": "Music"
    },
    {
      "name": "MusicHeart",
      "username": "MusicHeart",
      "datePost": "Dec 13 2025 7:48PM",
      "content": "Let Down (Remastered) - Radiohead",
      "iframe": "https://www.youtube.com/embed/ZVgHPSyEIqk",
      "video": "",
      "image": "",
      "likes": 546873,
      "liked": false,
      "topic": "Music"
    },
    {
      "name": "tae",
      "username": "taeOriginal",
      "datePost": "Dec 13 2025 7:47PM",
      "content": "Meko Brings me a warning message for posting furries",
      "iframe": "",
      "video": "",
      "image": "",
      "likes": 35465,
      "liked": false,
      "topic": "Meko"
    },
    {
      "name": "Pawa",
      "username": "Pawa",
      "datePost": "Dec 13 2025 2:28PM",
      "content": "❤️",
      "iframe": "",
      "video": "https://i.imgur.com/CTPxgmR.mp4",
      "image": "",
      "likes": 534341,
      "liked": false,
      "topic": "Pets"
    },
    {
      "name": "Pawa",
      "username": "Pawa",
      "datePost": "Dec 13 2025 2:27PM",
      "content": "Cute lil birdy",
      "iframe": "",
      "video": "https://i.imgur.com/A0SCb3V.mp4",
      "image": "",
      "likes": 7946,
      "liked": false,
      "topic": "Birds"
    },
    {
      "name": "Pawa",
      "username": "Pawa",
      "datePost": "Dec 13 2025 2:27PM",
      "content": "So cute❤️❤️❤️❤️❤️❤️",
      "iframe": "",
      "video": "https://i.imgur.com/GdgkNGd.mp4",
      "image": "",
      "likes": 83494,
      "liked": false,
      "topic": "Cats"
    },
    {
      "name": "Pawa",
      "username": "Pawa",
      "datePost": "Dec 13 2025 2:26PM",
      "content": "",
      "iframe": "",
      "video": "https://i.imgur.com/mlDQs07.mp4",
      "image": "",
      "likes": 56465,
      "liked": false,
      "topic": "Cats"
    },
    {
      "name": "UASE",
      "username": "UASE",
      "datePost": "Dec 13 2025 2:24PM",
      "content": "",
      "iframe": "",
      "video": "https://i.imgur.com/5oJAiBX.mp4",
      "image": "",
      "likes": 3412,
      "liked": false,
      "topic": "Music"
    },
    {
      "name": "KINGCONTENT",
      "username": "KINGCONTENT",
      "datePost": "Dec 13 2025 2:24PM",
      "content": "I FOUND THIS OLD VIDEO IN A BLOG",
      "iframe": "",
      "video": "https://i.imgur.com/GuF7CJ8.mp4",
      "image": "",
      "likes": 86464,
      "liked": false,
      "topic": "Music"
    },
    {
      "name": "Effort",
      "username": "Effort",
      "datePost": "Dec 13 2025 2:23PM",
      "content": "Guitar",
      "iframe": "",
      "video": "https://i.imgur.com/pJDcFzf.mp4",
      "image": "",
      "likes": 964523,
      "liked": false,
      "topic": "Music"
    },
    {
      "name": "VideoShare",
      "username": "VideoShare",
      "datePost": "Dec 13 2025 2:22PM",
      "content": "These videos are old can be found in the scraped Server of meko",
      "iframe": "",
      "video": "https://i.imgur.com/apNUNBW.mp4",
      "image": "",
      "likes": 46531,
      "liked": false,
      "topic": "Music"
    },
    {
      "name": "VideoShare",
      "username": "VideoShare",
      "datePost": "Dec 13 2025 2:21PM",
      "content": "Cont",
      "iframe": "",
      "video": "https://i.imgur.com/vIvx90J.mp4",
      "image": "",
      "likes": 76461,
      "liked": false,
      "topic": "Music"
    },
    {
      "name": "VideoShare",
      "username": "VideoShare",
      "datePost": "Dec 13 2025 2:21PM",
      "content": "Absolute Medieval",
      "iframe": "",
      "video": "https://i.imgur.com/DvgAirz.mp4",
      "image": "",
      "likes": 9746,
      "liked": false,
      "topic": "Music"
    },
    {
      "name": "tae",
      "username": "taeOriginal",
      "datePost": "Dec 13 2025 2:20PM",
      "content": "Talented",
      "iframe": "",
      "video": "https://i.imgur.com/x72w0cN.mp4",
      "image": "",
      "likes": 1374,
      "liked": false,
      "topic": "Music"
    },
    {
      "name": "RandomPerson",
      "username": "RandomPerson",
      "datePost": "Dec 13 2025 2:19PM",
      "content": "WATERMELON",
      "iframe": "",
      "video": "https://i.imgur.com/zCQs1ld.mp4",
      "image": "",
      "likes": 234564,
      "liked": false,
      "topic": "Music"
    },
    {
      "name": "RandomPerson",
      "username": "RandomPerson",
      "datePost": "Dec 13 2025 2:19PM",
      "content": "Airbag",
      "iframe": "",
      "video": "https://i.imgur.com/2agnP3J.mp4",
      "image": "",
      "likes": 7946,
      "liked": false,
      "topic": "Music"
    },
    {
      "name": "RandomPerson",
      "username": "RandomPerson",
      "datePost": "Dec 13 2025 2:18PM",
      "content": "Eeeeee",
      "iframe": "",
      "video": "https://i.imgur.com/xnYmfNJ.mp4",
      "image": "",
      "likes": 1334,
      "liked": false,
      "topic": "Music"
    },
    {
      "name": "RandomPerson",
      "username": "RandomPerson",
      "datePost": "Dec 13 2025 2:17PM",
      "content": "",
      "iframe": "",
      "video": "https://i.imgur.com/sj1nT1y.mp4",
      "image": "",
      "likes": 2494,
      "liked": false,
      "topic": "Foods"
    },
    {
      "name": "Cook",
      "username": "Cook",
      "datePost": "Dec 13 2025 2:16PM",
      "content": "Spam",
      "iframe": "",
      "video": "https://i.imgur.com/lMVC3mC.mp4",
      "image": "",
      "likes": 2314,
      "liked": false,
      "topic": "Foods"
    },
    {
      "name": "KINGCONTENT",
      "username": "KINGCONTENT",
      "datePost": "Dec 13 2025 2:15PM",
      "content": "The Recipey is old but is golden",
      "iframe": "",
      "video": "https://i.imgur.com/dfhrZ0W.mp4",
      "image": "",
      "likes": 13446,
      "liked": false,
      "topic": "Drinks"
    },
    {
      "name": "RandomPerson",
      "username": "RandomPerson",
      "datePost": "Dec 13 2025 2:14PM",
      "content": "Meko Been Bugging lately cant post more",
      "iframe": "",
      "video": "https://i.imgur.com/dv6jBoa.mp4",
      "image": "",
      "likes": 89494,
      "liked": false,
      "topic": "Random"
    },
    {
      "name": "RandomPerson",
      "username": "RandomPerson",
      "datePost": "Dec 13 2025 2:12PM",
      "content": "",
      "iframe": "",
      "video": "https://i.imgur.com/57oGLPY.mp4",
      "image": "",
      "likes": 1324,
      "liked": false,
      "topic": "Random"
    },
    {
      "name": "Meme",
      "username": "Meme",
      "datePost": "Dec 13 2025 2:09PM",
      "content": "😭",
      "iframe": "",
      "video": "https://i.imgur.com/5WbkYzg.mp4",
      "image": "",
      "likes": 2346,
      "liked": false,
      "topic": "Funny"
    },
    {
      "name": "Meme",
      "username": "Meme",
      "datePost": "Dec 13 2025 2:09PM",
      "content": "A Ostrich😭",
      "iframe": "",
      "video": "https://i.imgur.com/hp0tVOl.mp4",
      "image": "",
      "likes": 56451,
      "liked": false,
      "topic": "Funny"
    },
    {
      "name": "Meme",
      "username": "Meme",
      "datePost": "Dec 13 2025 2:08PM",
      "content": "Fixed✔️",
      "iframe": "",
      "video": "https://i.imgur.com/iohdH21.mp4",
      "image": "",
      "likes": 87643,
      "liked": false,
      "topic": "Funny"
    },
    {
      "name": "Meme",
      "username": "Meme",
      "datePost": "Dec 13 2025 2:07PM",
      "content": "Meme Original Error",
      "iframe": "",
      "video": "https://i.imgur.com/eehrdLs.mp4",
      "image": "",
      "likes": 43431,
      "liked": false,
      "topic": "Meme"
    },
    {
      "name": "Ofer",
      "username": "Ofer",
      "datePost": "Dec 13 2025 2:06PM",
      "content": "哈哈哈哈。结尾太搞笑了",
      "iframe": "",
      "video": "https://i.imgur.com/x4Vqg7S.mp4",
      "image": "",
      "likes": 3421,
      "liked": false,
      "topic": "FunnyChina"
    },
    {
      "name": "Chizo",
      "username": "Chizo",
      "datePost": "Dec 13 2025 2:04PM",
      "content": "非常可怕",
      "iframe": "",
      "video": "https://i.imgur.com/QzceQO9.mp4",
      "image": "",
      "likes": 53431,
      "liked": false,
      "topic": "Disaster"
    },
    {
      "name": "Chizo",
      "username": "Chizo",
      "datePost": "Dec 13 2025 2:02PM",
      "content": "你的英语不可能那么差吧，真的。",
      "iframe": "",
      "video": "https://i.imgur.com/I1beXr8.mp4",
      "image": "",
      "likes": 35946,
      "liked": false,
      "topic": "Funny"
    },
    {
      "name": "Chizo",
      "username": "Chizo",
      "datePost": "Dec 13 2025 2:01PM",
      "content": "这在2020年真是太搞笑了🤣",
      "iframe": "",
      "video": "https://i.imgur.com/lVeL4NA.mp4",
      "image": "",
      "likes": 56495,
      "liked": false,
      "topic": "Funny Prank"
    },
    {
      "name": "Haystack",
      "username": "Haystack",
      "datePost": "Dec 13 2025 2:00PM",
      "content": "Lol",
      "iframe": "",
      "video": "https://i.imgur.com/9HDZVBw.mp4",
      "image": "",
      "likes": 8346,
      "liked": false,
      "topic": "Funny"
    },
    {
      "name": "Haystack",
      "username": "Haystack",
      "datePost": "Dec 13 2025 1:59PM",
      "content": "Offguard",
      "iframe": "",
      "video": "https://i.imgur.com/EvsFwcN.mp4",
      "image": "",
      "likes": 53495,
      "liked": false,
      "topic": "Funny"
    },
    {
      "name": "VideoShare",
      "username": "VideoShare",
      "datePost": "Dec 13 2025 1:59PM",
      "content": "Funny",
      "iframe": "",
      "video": "https://i.imgur.com/38v2WZA.mp4",
      "image": "",
      "likes": 79344,
      "liked": false,
      "topic": "Funny"
    },
    {
      "name": "VideoShare",
      "username": "VideoShare",
      "datePost": "Dec 13 2025 1:58PM",
      "content": "",
      "iframe": "",
      "video": "https://i.imgur.com/PTqleE6.mp4",
      "image": "",
      "likes": 4645,
      "liked": false,
      "topic": "Funny"
    },
    {
      "name": "VideoShare",
      "username": "VideoShare",
      "datePost": "Dec 13 2025 1:57PM",
      "content": "",
      "iframe": "",
      "video": "https://i.imgur.com/mdvrDP3.mp4",
      "image": "",
      "likes": 13164,
      "liked": false,
      "topic": "Funny"
    },
    {
      "name": "VideoShare",
      "username": "VideoShare",
      "datePost": "Dec 13 2025 1:56PM",
      "content": "",
      "iframe": "",
      "video": "https://i.imgur.com/HzZX5yH.mp4",
      "image": "",
      "likes": 53491,
      "liked": false,
      "topic": "Funny"
    },
    {
      "name": "Femination",
      "username": "Femination",
      "datePost": "Dec 13 2025 1:56PM",
      "content": "She was too hot to hold down his pee",
      "iframe": "",
      "video": "https://i.imgur.com/kNQGSV1.mp4",
      "image": "",
      "likes": 6431,
      "liked": false,
      "topic": "Random"
    },
    {
      "name": "Cook",
      "username": "Cook",
      "datePost": "Dec 13 2025 1:53PM",
      "content": "Call me Steph Curry the way I be handling these balls",
      "iframe": "",
      "video": "https://i.imgur.com/nPURylQ.mp4",
      "image": "",
      "likes": 124365,
      "liked": false,
      "topic": "Cook"
    },
    {
      "name": "mo",
      "username": "Mok",
      "datePost": "Dec 13 2025 1:52PM",
      "content": "Dog Friend",
      "iframe": "",
      "video": "https://i.imgur.com/645R4t9.mp4",
      "image": "",
      "likes": 955,
      "liked": false,
      "topic": "Dogs"
    },
    {
      "name": "Sak",
      "username": "Sak",
      "datePost": "Dec 13 2025 1:51PM",
      "content": "Proper Research",
      "iframe": "",
      "video": "https://i.imgur.com/7g8ASfJ.mp4",
      "image": "",
      "likes": 56161,
      "liked": false,
      "topic": "Random"
    },
    {
      "name": "Egola",
      "username": "Egola",
      "datePost": "Dec 13 2025 1:49PM",
      "content": "Heres a Catch",
      "iframe": "",
      "video": "https://i.imgur.com/apkuTYP.mp4",
      "image": "",
      "likes": 16543,
      "liked": false,
      "topic": "WildLife"
    },
    {
      "name": "tan",
      "username": "tan",
      "datePost": "Dec 13 2025 1:47PM",
      "content": "",
      "iframe": "",
      "video": "https://i.imgur.com/Pz9T0Ov.mp4",
      "image": "",
      "likes": 5349,
      "liked": false,
      "topic": "Funny"
    },
    {
      "name": "Lady",
      "username": "Lady",
      "datePost": "Dec 13 2025 1:46PM",
      "content": "I think i downloaded the wrong lord of rings",
      "iframe": "",
      "video": "https://i.imgur.com/PeYRVq1.mp4",
      "image": "",
      "likes": 43465,
      "liked": false,
      "topic": "18+"
    },
    {
      "name": "Ofroad",
      "username": "Ofroad",
      "datePost": "Dec 13 2025 1:45PM",
      "content": "Good news, everyone! You can get 50-year mortgage!",
      "iframe": "",
      "video": "",
      "image": "https://i.imgur.com/YAWWnVH_d.webp?maxwidth=520&shape=thumb&fidelity=high",
      "likes": 98349,
      "liked": false,
      "topic": "Random"
    },
    {
      "name": "Twa",
      "username": "Twa",
      "datePost": "Dec 13 2025 1:44PM",
      "content": "Pole shenanigens",
      "iframe": "",
      "video": "https://i.imgur.com/Gg8ZZlF.mp4",
      "image": "",
      "likes": 4355,
      "liked": false,
      "topic": "Random"
    },
    {
      "name": "alone",
      "username": "alone",
      "datePost": "Dec 13 2025 2:47AM",
      "content": "",
      "iframe": "https://youtu.be/BMREe6Y9tNA?si=EBX22Vb_dcnPzRuB",
      "video": "",
      "image": "",
      "likes": 65452,
      "liked": false,
      "topic": "tired"
    },
    {
      "name": "Softy💓",
      "username": "Softy",
      "datePost": "Dec 13 2025 2:41AM",
      "content": "Send this to him💓",
      "iframe": "",
      "video": "",
      "image": "https://i.imgur.com/hIKeBzO_d.webp?maxwidth=520&shape=thumb&fidelity=high",
      "likes": 53461,
      "liked": false,
      "topic": "Couples"
    },
    {
      "name": "Oaklama",
      "username": "Oaklama",
      "datePost": "Dec 13 2025 2:38AM",
      "content": "Conservatives just want people to suffer.",
      "iframe": "",
      "video": "https://i.imgur.com/enkCORW.mp4",
      "image": "",
      "likes": 9846,
      "liked": false,
      "topic": "Random"
    },
    {
      "name": "Cook",
      "username": "Cook",
      "datePost": "Dec 13 2025 2:36AM",
      "content": "HOLIDAY FOOD😋🥞",
      "iframe": "",
      "video": "https://i.imgur.com/VWb8nHM.mp4",
      "image": "",
      "likes": 96452,
      "liked": false,
      "topic": "Foods"
    },
    {
      "name": "Teas",
      "username": "Teas",
      "datePost": "Dec 13 2025 2:33AM",
      "content": "We cannot afford to be happy",
      "iframe": "",
      "video": "",
      "image": "https://i.imgur.com/WHVAxJq_d.webp?maxwidth=520&shape=thumb&fidelity=high",
      "likes": 6445,
      "liked": false,
      "topic": "Random"
    },
    {
      "name": "EFFECTIVO",
      "username": "effectivo",
      "datePost": "Dec 13 2025 2:31AM",
      "content": "",
      "iframe": "",
      "video": "",
      "image": "https://i.imgur.com/KU196kz_d.webp?maxwidth=520&shape=thumb&fidelity=high",
      "likes": 2161,
      "liked": false,
      "topic": "Random"
    },
    {
      "name": "Oaklama",
      "username": "Oaklama",
      "datePost": "Dec 13 2025 2:30AM",
      "content": "Mike hates it because the actions represent a true majority and not a Trump bootlicking one",
      "iframe": "",
      "video": "",
      "image": "https://i.imgur.com/mjr3sUz_d.webp?maxwidth=760&fidelity=grand",
      "likes": 34242,
      "liked": false,
      "topic": "Random"
    },
    {
      "name": "Oaklama",
      "username": "Oaklama",
      "datePost": "Dec 13 2025 2:28AM",
      "content": "So True",
      "iframe": "",
      "video": "",
      "image": "https://i.imgur.com/ZBiPU5J_d.webp?maxwidth=520&shape=thumb&fidelity=high",
      "likes": 7656,
      "liked": false,
      "topic": "Reference"
    },
    {
      "name": "Oaklama",
      "username": "Oaklama",
      "datePost": "Dec 13 2025 2:27AM",
      "content": "Friday Mood",
      "iframe": "",
      "video": "",
      "image": "https://i.imgur.com/0LMhh4h_d.webp?maxwidth=520&shape=thumb&fidelity=high",
      "likes": 4364,
      "liked": false,
      "topic": "Random"
    },
    {
      "name": "Oaklama",
      "username": "Oaklama",
      "datePost": "Dec 13 2025 2:26AM",
      "content": "Not the best but is cute",
      "iframe": "",
      "video": "",
      "image": "https://i.imgur.com/Lxrbpfo_d.webp?maxwidth=520&shape=thumb&fidelity=high",
      "likes": 464965,
      "liked": false,
      "topic": "Random"
    },
    {
      "name": "Oaklama",
      "username": "Oaklama",
      "datePost": "Dec 13 2025 2:25AM",
      "content": "Jimmy Kimmel on Trump: \"Everyone treats him like he's three years old. He needs a lot of attention. He needs immediate gratification. He needs constant praise for nothing. He takes nap time. They order him McDonald's. He gets ice cream after dinner ..",
      "iframe": "",
      "video": "https://i.imgur.com/RJKBduO.mp4",
      "image": "",
      "likes": 46454,
      "liked": false,
      "topic": "Random"
    },
    {
      "name": "Memes",
      "username": "Memes",
      "datePost": "Dec 13 2025 2:23AM",
      "content": "",
      "iframe": "",
      "video": "https://i.imgur.com/9FZQ5n2.mp4",
      "image": "",
      "likes": 6446,
      "liked": false,
      "topic": "Meme"
    },
    {
      "name": "Memes",
      "username": "Memes",
      "datePost": "Dec 13 2025 2:21AM",
      "content": "",
      "iframe": "",
      "video": "https://i.imgur.com/xRT8prI.mp4",
      "image": "",
      "likes": 56435,
      "liked": false,
      "topic": "Meme"
    },
    {
      "name": "Safe",
      "username": "Safe",
      "datePost": "Dec 13 2025 2:20AM",
      "content": "",
      "iframe": "",
      "video": "",
      "image": "https://i.imgur.com/eM8TCQ5_d.webp?maxwidth=520&shape=thumb&fidelity=high",
      "likes": 64543,
      "liked": false,
      "topic": "Furries"
    },
    {
      "name": "Snuff",
      "username": "Snuff",
      "datePost": "Dec 13 2025 2:19AM",
      "content": "Secret Mermaid😭",
      "iframe": "",
      "video": "",
      "image": "https://i.imgur.com/6BGdEzw_d.webp?maxwidth=520&shape=thumb&fidelity=high",
      "likes": 4334,
      "liked": false,
      "topic": "Stories"
    },
    {
      "name": "tae",
      "username": "taeOriginal",
      "datePost": "Dec 13 2025 2:18AM",
      "content": "Wooden Pot",
      "iframe": "",
      "video": "https://i.imgur.com/Sn7WtSC.mp4",
      "image": "",
      "likes": 7346,
      "liked": false,
      "topic": "Random"
    },
    {
      "name": "tae",
      "username": "taeOriginal",
      "datePost": "Dec 13 2025 2:18AM",
      "content": "",
      "iframe": "",
      "video": "https://i.imgur.com/u6hwm9e.mp4",
      "image": "",
      "likes": 5346,
      "liked": false,
      "topic": "Random"
    },
    {
      "name": "Sj",
      "username": "Sj",
      "datePost": "Dec 13 2025 2:17AM",
      "content": "Knights of Guinevere:ScareTactics",
      "iframe": "",
      "video": "",
      "image": "https://i.imgur.com/plmm5jc_d.webp?maxwidth=520&shape=thumb&fidelity=high",
      "likes": 3124,
      "liked": false,
      "topic": "comics"
    },
    {
      "name": "Teas",
      "username": "Teas",
      "datePost": "Dec 13 2025 2:15AM",
      "content": "",
      "iframe": "",
      "video": "https://i.imgur.com/DtRNs2D.mp4",
      "image": "",
      "likes": 5343,
      "liked": false,
      "topic": "CORRUPTION!"
    },
    {
      "name": "Safe",
      "username": "Safe",
      "datePost": "Dec 13 2025 2:14AM",
      "content": "Furries are cutes",
      "iframe": "",
      "video": "",
      "image": "https://i.imgur.com/lR8Xh6b_d.webp?maxwidth=520&shape=thumb&fidelity=high",
      "likes": 32346,
      "liked": false,
      "topic": "Furries"
    },
    {
      "name": "Tase",
      "username": "tasedk",
      "datePost": "Dec 13 2025 2:13AM",
      "content": "ICE Confronted by patriot",
      "iframe": "",
      "video": "https://i.imgur.com/ETQf2Lt.mp4",
      "image": "",
      "likes": 5364,
      "liked": false,
      "topic": "ICE Corrupt"
    },
    {
      "name": "User737492928493",
      "username": "User737492928493",
      "datePost": "Dec 13 2025 2:10AM",
      "content": "Happy Birthday",
      "iframe": "",
      "video": "https://i.imgur.com/ZqzAbd9.mp4",
      "image": "",
      "likes": 313,
      "liked": false,
      "topic": "Random"
    },
    {
      "name": "Sevk",
      "username": "Gekr",
      "datePost": "Dec 13 2025 2:09AM",
      "content": "Spread the word!",
      "iframe": "",
      "video": "",
      "image": "https://i.imgur.com/rltmc1z_d.webp?maxwidth=520&shape=thumb&fidelity=high",
      "likes": 342,
      "liked": false,
      "topic": "Random"
    },
    {
      "name": "Femination",
      "username": "Femination",
      "datePost": "Dec 13 2025 2:08AM",
      "content": "PHOTO 5",
      "iframe": "",
      "video": "",
      "image": "https://i.imgur.com/3JlatER_d.webp?maxwidth=760&fidelity=grand",
      "likes": 46466,
      "liked": false,
      "topic": "Cosplay"
    },
    {
      "name": "Femination",
      "username": "Femination",
      "datePost": "Dec 13 2025 2:07AM",
      "content": "PHOTO 4",
      "iframe": "",
      "video": "",
      "image": "https://i.imgur.com/LCAlZLs_d.webp?maxwidth=760&fidelity=grand",
      "likes": 56435,
      "liked": false,
      "topic": "Cosplay"
    },
    {
      "name": "Femination",
      "username": "Femination",
      "datePost": "Dec 13 2025 2:07AM",
      "content": "PHOTO 3",
      "iframe": "",
      "video": "",
      "image": "https://i.imgur.com/IVpFAhl_d.webp?maxwidth=760&fidelity=grand",
      "likes": 24356,
      "liked": false,
      "topic": "Cosplay"
    },
    {
      "name": "Femination",
      "username": "Femination",
      "datePost": "Dec 13 2025 2:06AM",
      "content": "SOUNDWAVE GIRL COSPLAY PHOTO 2",
      "iframe": "",
      "video": "",
      "image": "https://i.imgur.com/otD0wtl_d.webp?maxwidth=760&fidelity=grand",
      "likes": 35495,
      "liked": false,
      "topic": "Cosplay"
    },
    {
      "name": "Femination",
      "username": "Femination",
      "datePost": "Dec 13 2025 2:05AM",
      "content": "SOUNDWAVE GIRL COSPLAY PHOTO 1",
      "iframe": "",
      "video": "",
      "image": "https://i.imgur.com/cn07xSo_d.webp?maxwidth=760&fidelity=grand",
      "likes": 23464,
      "liked": false,
      "topic": "Cosplay"
    },
    {
      "name": "HA",
      "username": "hAh",
      "datePost": "Dec 13 2025 1:18AM",
      "content": "Happy FF",
      "iframe": "",
      "video": "",
      "image": "https://i.imgur.com/erUjGJE_d.webp?maxwidth=520&shape=thumb&fidelity=high",
      "likes": 43,
      "liked": false,
      "topic": "Funny"
    },
    {
      "name": "ef",
      "username": "rose9284",
      "datePost": "Dec 12 2025 11:20PM",
      "content": "@chinifochina ",
      "iframe": "",
      "video": "",
      "image": "https://i.imgur.com/HBUXLoV_d.webp?maxwidth=760&fidelity=grand",
      "likes": 3464,
      "liked": false,
      "topic": "Cosplay"
    },
    {
      "name": "ChiniFo",
      "username": "chinifochina@",
      "datePost": "Dec 12 2025 11:19PM",
      "content": "Cosplayer",
      "iframe": "",
      "video": "",
      "image": "https://i.imgur.com/cCWB4A0_d.webp?maxwidth=1520&fidelity=grand",
      "likes": 56364,
      "liked": false,
      "topic": "Cosplay"
    },
    {
      "name": "ChiniFo",
      "username": "chinifochina@",
      "datePost": "Dec 12 2025 11:17PM",
      "content": "😭",
      "iframe": "",
      "video": "https://i.imgur.com/II20Ran.mp4",
      "image": "",
      "likes": 56435,
      "liked": false,
      "topic": "Meme"
    },
    {
      "name": "tae",
      "username": "TaeOriginal",
      "datePost": "Dec 12 2025 11:15PM",
      "content": "WOAH",
      "iframe": "",
      "video": "",
      "image": "https://i.imgur.com/7t89UZ1_d.webp?maxwidth=520&shape=thumb&fidelity=high",
      "likes": 6556,
      "liked": false,
      "topic": "Education"
    },
    {
      "name": "tae",
      "username": "TaeOriginal",
      "datePost": "Dec 12 2025 11:14PM",
      "content": "Stoked",
      "iframe": "",
      "video": "https://i.imgur.com/IdJgWuh.mp4",
      "image": "",
      "likes": 35646,
      "liked": false,
      "topic": "Random"
    },
    {
      "name": "tae",
      "username": "TaeOriginal",
      "datePost": "Dec 12 2025 11:13PM",
      "content": "ABC always be closing",
      "iframe": "",
      "video": "https://i.imgur.com/4F4k2rS.mp4",
      "image": "",
      "likes": 834653,
      "liked": false,
      "topic": "Random"
    },
    {
      "name": "Ksn",
      "username": "9282ks",
      "datePost": "Dec 12 2025 11:12PM",
      "content": "Opss i guess",
      "iframe": "",
      "video": "",
      "image": "https://i.imgur.com/WOUSkE8_d.webp?maxwidth=520&shape=thumb&fidelity=high",
      "likes": 655,
      "liked": false,
      "topic": "AI"
    },
    {
      "name": "MiaREAD",
      "username": "Mia92",
      "datePost": "Dec 12 2025 11:10PM",
      "content": "I totally get it now 100%",
      "iframe": "",
      "video": "https://i.imgur.com/USreqZx.mp4",
      "image": "",
      "likes": 64532,
      "liked": false,
      "topic": "Podcast"
    },
    {
      "name": "CatsVideos",
      "username": "catsvideo838",
      "datePost": "Dec 12 2025 11:07PM",
      "content": "Sam, Merry, Pippin, and Frodo are going back to the humane society tomorrow morning to be fixed and put up for adoption, so I had to pull their dry food up earlier but they deserve one more can of wet food. I had to do it. Oh my GOD listen to their purrs. I am going to miss them so much.",
      "iframe": "",
      "video": "https://i.imgur.com/5o2kx61.mp4",
      "image": "",
      "likes": 754623,
      "liked": false,
      "topic": "Cats"
    },
    {
      "name": "CatsVideos",
      "username": "catsvideo838",
      "datePost": "Dec 12 2025 11:06PM",
      "content": "I wasnt Expecting this🐈",
      "iframe": "",
      "video": "https://i.imgur.com/J25T2N8.mp4",
      "image": "",
      "likes": 35645,
      "liked": false,
      "topic": "Cats"
    },
    {
      "name": "CatsVideos",
      "username": "catsvideo838",
      "datePost": "Dec 12 2025 11:05PM",
      "content": "The LotR kittens are getting fixed tomorrow morning so I had to pull the food out of the kitten room because they can't eat after midnight. I put the bowls of food in the bathtub thinking it was hidden but Scooty and Maddy found it almost immediately. Whatever. They can have \"treats.\" I can't win",
      "iframe": "",
      "video": "https://i.imgur.com/DfpKyr5.mp4",
      "image": "",
      "likes": 452679,
      "liked": false,
      "topic": "Cats"
    },
    {
      "name": "rs6000",
      "username": "rs6000",
      "datePost": "Dec 12 2025 11:03PM",
      "content": "REDDEST AUORA EVER",
      "iframe": "",
      "video": "https://i.imgur.com/ujq0dkb.mp4",
      "image": "",
      "likes": 152380,
      "liked": false,
      "topic": "Antartica"
    },
    {
      "name": "rs6000",
      "username": "rs6000",
      "datePost": "Dec 12 2025 11:02PM",
      "content": "Your presence may change the outcome, just show up\n",
      "iframe": "",
      "video": "https://i.imgur.com/xM3z21q.mp4",
      "image": "",
      "likes": 5946,
      "liked": false,
      "topic": "Lefty"
    },
    {
      "name": "rs6000",
      "username": "rs6000",
      "datePost": "Dec 12 2025 11:00PM",
      "content": "The Timing",
      "iframe": "",
      "video": "https://i.imgur.com/jMljxYx.mp4",
      "image": "",
      "likes": 23194,
      "liked": false,
      "topic": "Random"
    },
    {
      "name": "rs6000",
      "username": "rs6000",
      "datePost": "Dec 12 2025 10:59PM",
      "content": "A hermit crab moving into a modern house",
      "iframe": "",
      "video": "https://i.imgur.com/7mO0g1o.mp4",
      "image": "",
      "likes": 2316,
      "liked": false,
      "topic": "HermitCrab"
    },
    {
      "name": "Naza",
      "username": "Naza",
      "datePost": "Dec 12 2025 10:58PM",
      "content": "Asteroid Bennu Contains Tryptophan and Ribose",
      "iframe": "",
      "video": "https://i.imgur.com/sP432PL_lq.mp4",
      "image": "",
      "likes": 3564,
      "liked": false,
      "topic": "Space"
    },
    {
      "name": "Cook",
      "username": "Cook",
      "datePost": "Dec 12 2025 10:56PM",
      "content": "Crispy Chicken Caesar Sandwich",
      "iframe": "",
      "video": "https://i.imgur.com/Iat8NA3.mp4",
      "image": "",
      "likes": 965423,
      "liked": false,
      "topic": ""
    },
    {
      "name": "tae",
      "username": "taeOriginal",
      "datePost": "Dec 12 2025 10:54PM",
      "content": "Let me take that for you, thank you",
      "iframe": "",
      "video": "https://i.imgur.com/2P3A1nh.mp4",
      "image": "",
      "likes": 2395,
      "liked": false,
      "topic": "Funny"
    },
    {
      "name": "Pawa",
      "username": "Pawa",
      "datePost": "Dec 12 2025 10:53PM",
      "content": "Cute",
      "iframe": "",
      "video": "https://i.imgur.com/Mu0HsJT.mp4",
      "image": "",
      "likes": 0,
      "liked": false,
      "topic": "Puppies"
    },
    {
      "name": "Memes",
      "username": "Memes",
      "datePost": "Dec 12 2025 10:51PM",
      "content": "",
      "iframe": "",
      "video": "https://i.imgur.com/zJRL242.mp4",
      "image": "",
      "likes": 35642,
      "liked": false,
      "topic": "Funny"
    },
    {
      "name": "Jeywalk",
      "username": "Jeywalk",
      "datePost": "Dec 12 2025 10:46PM",
      "content": "I dont know what your talking Riley",
      "iframe": "",
      "video": "https://i.imgur.com/b91gMbb.mp4",
      "image": "",
      "likes": 3836,
      "liked": false,
      "topic": "Comedy"
    },
    {
      "name": "Femination",
      "username": "Femination",
      "datePost": "Dec 12 2025 10:44PM",
      "content": "Merry Christmass",
      "iframe": "",
      "video": "",
      "image": "https://i.imgur.com/NCRr0YZ_d.webp?maxwidth=520&shape=thumb&fidelity=high",
      "likes": 326,
      "liked": false,
      "topic": "ShowOff"
    },
    {
      "name": "tae",
      "username": "taeOriginal",
      "datePost": "Dec 12 2025 10:29PM",
      "content": "Look At Thsi car",
      "iframe": "",
      "video": "https://i.imgur.com/DTQiaQp.mp4",
      "image": "",
      "likes": 52684,
      "liked": false,
      "topic": "Memes"
    },
    {
      "name": "Maya L",
      "username": "JustCantEven",
      "datePost": "Dec 12 2025 10:29PM",
      "content": "It just gets more unhinged",
      "iframe": "",
      "video": "",
      "image": "https://i.imgur.com/e6e4GEK_d.webp?maxwidth=520&shape=thumb&fidelity=high",
      "likes": 629,
      "liked": false,
      "topic": "Memes"
    },
    {
      "name": "Maya L",
      "username": "JustCantEven",
      "datePost": "Dec 12 2025 10:25PM",
      "content": "",
      "iframe": "",
      "video": "",
      "image": "https://i.imgur.com/cYSkUqp_d.webp?maxwidth=520&shape=thumb&fidelity=high",
      "likes": 839,
      "liked": false,
      "topic": "Memes"
    },
    {
      "name": "Maya L",
      "username": "JustCantEven",
      "datePost": "Dec 12 2025 10:25PM",
      "content": "My 'I'm just gonna run a quick errand' turned into a 3-hour saga. Why is the universe testing me on a Friday? I just wanted milk. Send snacks.",
      "iframe": "",
      "video": "",
      "image": "",
      "likes": 711,
      "liked": false,
      "topic": "Venting"
    },
    {
      "name": "Maya L",
      "username": "JustCantEven",
      "datePost": "Dec 12 2025 10:25PM",
      "content": "My 'I'm just gonna run a quick errand' turned into a 3-hour saga. Why is the universe testing me on a Friday? I just wanted milk. Send snacks.",
      "iframe": "",
      "video": "",
      "image": "",
      "likes": 711,
      "liked": false,
      "topic": "Venting"
    },
    {
      "name": "Noah T",
      "username": "SlayTheDay",
      "datePost": "Dec 12 2025 10:23PM",
      "content": "Lowkey obsessed with this new color palette I found. The neutrals are giving main character energy. 🎨✨ Check out the inspiration here: https://designblog.com/color-palettes/earthy-neutrals",
      "iframe": "",
      "video": "",
      "image": "https://cdn.assets.com/slaytheday/neutral_palette_photo.jpg",
      "likes": 1950,
      "liked": true,
      "topic": "Aesthetics"
    },
    {
      "name": "Jess W",
      "username": "FinancialGworl",
      "datePost": "Dec 12 2025 10:20PM",
      "content": "The way my bank account looks at me after I remember I have bills due. It's giving silence and disappointment. We'll bounce back, bestie. Read how to budget for next month: https://financehacks.com/emergency-budgeting-guide",
      "iframe": "",
      "video": "",
      "image": "",
      "likes": 602,
      "liked": false,
      "topic": "Money"
    },
    {
      "name": "Elias K",
      "username": "RetroGrade",
      "datePost": "Dec 12 2025 10:18PM",
      "content": "Storytime: Did anyone else think those tiny, weirdly textured plastic rings from the 2000s were peak jewelry? I was a menace, honestly. Article on 2000s trends: https://popculturethrowbacks.com/2000s-jewelry-comeback",
      "iframe": "",
      "video": "",
      "image": "",
      "likes": 477,
      "liked": true,
      "topic": "Nostalgia"
    },
    {
      "name": "Sarah M",
      "username": "PettyPigeon",
      "datePost": "Dec 12 2025 10:15PM",
      "content": "I think the opposite of adulting is just buying yourself that random plushie you saw in the clearance bin. Self-care, look it up. Find cute plushies here: https://clearancebin.com/random-plushie-sale",
      "iframe": "",
      "video": "",
      "image": "",
      "likes": 1401,
      "liked": false,
      "topic": "Random"
    },
    {
      "name": "Alex R",
      "username": "CodeConnoisseur",
      "datePost": "Dec 12 2025 10:12PM",
      "content": "Just spent 4 hours tracking down a bug only to realize I used '==' instead of '==='. The rubber duck is judging me hard right now. #DevLife Learn the difference: https://devdocs.io/js/comparison-operators",
      "iframe": "",
      "video": "",
      "image": "",
      "likes": 2548,
      "liked": true,
      "topic": "Tech"
    },
    {
      "name": "Chloe B",
      "username": "GreenThumbGal",
      "datePost": "Dec 12 2025 10:09PM",
      "content": "My Monstera just put out a new leaf and it's HUGE. Feeling like a proud plant parent. 🌿💚 What are your favorite low-maintenance indoor plants? Read about Monstera care: https://planttips.org/monstera-leaf-care",
      "iframe": "",
      "video": "",
      "image": "https://cdn.assets.com/greenthumbgal/monstera_photo.jpg",
      "likes": 887,
      "liked": false,
      "topic": "Gardening"
    },
    {
      "name": "Ben F",
      "username": "MovieBuffBen",
      "datePost": "Dec 12 2025 10:05PM",
      "content": "Rewatching a classic and realizing all the subtle foreshadowing I missed as a kid. This film is a masterpiece. Highly recommend! (It's Jaws, btw) See the trailer: https://www.youtube.com/embed/movie-jaws-trailer",
      "iframe": "https://www.youtube.com/embed/movie-jaws-trailer",
      "video": "",
      "image": "",
      "likes": 321,
      "liked": true,
      "topic": "Entertainment"
    },
    {
      "name": "Olivia P",
      "username": "WanderLustOP",
      "datePost": "Dec 12 2025 10:02PM",
      "content": "Just booked my trip for April! Trading city views for mountain air. Time to start making the playlist. Any destination recommendations for next time? Check out my itinerary: https://travelblog.com/april-mountain-trip",
      "iframe": "",
      "video": "",
      "image": "",
      "likes": 1655,
      "liked": false,
      "topic": "Travel"
    },
    {
      "name": "Ethan H",
      "username": "QuietThinker",
      "datePost": "Dec 12 2025 09:58PM",
      "content": "Spent the last hour just sitting in silence and listening to the rain. Sometimes you need to let the world be loud so your own thoughts can be quiet. Good article on mindfulness: https://wellnessdaily.com/quiet-mind-techniques",
      "iframe": "",
      "video": "",
      "image": "",
      "likes": 912,
      "liked": true,
      "topic": "Reflect"
    },
    {
      "name": "Hannah S",
      "username": "BookWormHS",
      "datePost": "Dec 12 2025 09:55PM",
      "content": "Finished 'The Midnight Library' tonight. Truly beautiful. Makes you wonder about all the roads not taken. 📚✨ What's the last book that made you think? Buy the book here: https://greatbooks.com/midnight-library",
      "iframe": "",
      "video": "",
      "image": "",
      "likes": 1120,
      "liked": true,
      "topic": "Books"
    },
    {
      "name": "Ryan Z",
      "username": "TheGamerHub",
      "datePost": "Dec 12 2025 09:50PM",
      "content": "Lag is my villain origin story. Losing a ranked match because of one shaky connection is peak frustration. Time for a ping test. 😡 How to check your ping: https://gamingsupport.com/network-ping-test",
      "iframe": "",
      "video": "",
      "image": "",
      "likes": 650,
      "liked": false,
      "topic": "Gaming"
    },
    {
      "name": "Laura D",
      "username": "RecipeRider",
      "datePost": "Dec 12 2025 09:47PM",
      "content": "New favorite dinner unlocked: Sheet Pan Lemon Herb Chicken and Veggies. Minimal clean-up, maximum flavor. Weekend win! 🍽️ Get the recipe: https://allrecipes.com/lemon-herb-chicken-sheet-pan",
      "iframe": "",
      "video": "https://cdn.assets.com/reciperider/chicken_recipe.mp4",
      "image": "",
      "likes": 2105,
      "liked": true,
      "topic": "Food"
    },
    {
      "name": "Kevin J",
      "username": "CryptoKingKJ",
      "datePost": "Dec 12 2025 09:45PM",
      "content": "Just a friendly reminder to secure your digital assets. Not your keys, not your coins! Stay safe out there, people. 🔒 Read about wallet security: https://cryptonews.com/wallet-security-tips",
      "iframe": "",
      "video": "",
      "image": "",
      "likes": 980,
      "liked": false,
      "topic": "Finance"
    },
    {
      "name": "Mia V",
      "username": "TheFashionista",
      "datePost": "Dec 12 2025 09:40PM",
      "content": "Does anyone else have that one item in their closet they bought years ago but still feels brand new and perfect? Mine is a vintage leather jacket.",
      "iframe": "",
      "video": "",
      "image": "https://cdn.assets.com/thefashionista/jacket_photo.jpg",
      "likes": 1720,
      "liked": true,
      "topic": "Fashion"
    },
    {
      "name": "Daniel P",
      "username": "ScienceGuyDP",
      "datePost": "Dec 12 2025 09:35PM",
      "content": "Fascinated by the James Webb Space Telescope's latest image drop. The sheer scale and beauty of the universe is humbling. 🔭🌌 See the images here: https://nasa.gov/jwst/latest-discoveries-dec-2025",
      "iframe": "",
      "video": "",
      "image": "https://cdn.assets.com/scienceguydp/jwst_image.jpg",
      "likes": 2801,
      "liked": true,
      "topic": "Science"
    },
    {
      "name": "Zoe C",
      "username": "MindfulZen",
      "datePost": "Dec 12 2025 09:30PM",
      "content": "Remember to breathe. If you only accomplish one thing today, let it be acknowledging your efforts. That's enough. 💖 Try this 5-minute meditation: https://mindfulapp.com/quick-breathing-exercise",
      "iframe": "",
      "video": "",
      "image": "",
      "likes": 1300,
      "liked": true,
      "topic": "Wellness"
    },
    {
      "name": "Marcus E",
      "username": "DIYKingME",
      "datePost": "Dec 12 2025 09:25PM",
      "content": "Finished mounting the new shelf in the garage! Pro-tip: always measure twice, drill once. Saved me a huge headache today. Full tutorial link:",
      "iframe": "",
      "video": "https://cdn.assets.com/diykingme/shelf_tutorial.mp4",
      "image": "",
      "likes": 765,
      "liked": false,
      "topic": "DIY"
    },
    {
      "name": "Kelly A",
      "username": "CoffeeQueen",
      "datePost": "Dec 12 2025 09:20PM",
      "content": "Perfect coffee tip: a tiny pinch of sea salt in your grounds cuts the bitterness and brings out the chocolate notes. Try it! Read the science: https://foodresearch.org/coffee-salt-experiment",
      "iframe": "",
      "video": "",
      "image": "",
      "likes": 1992,
      "liked": true,
      "topic": "Food"
    },
    {
      "name": "Liam B",
      "username": "TheMusician",
      "datePost": "Dec 12 2025 09:15PM",
      "content": "Experimenting with a new looper pedal tonight. It's like having a whole band in a box. So many cool soundscapes possible! 🎸 See the pedal demo here: https://www.youtube.com/embed/looper-pedal-review",
      "iframe": "https://www.youtube.com/embed/looper-pedal-review",
      "video": "",
      "image": "",
      "likes": 550,
      "liked": false,
      "topic": "Music"
    },
    {
      "name": "Grace F",
      "username": "WorldCitizenGF",
      "datePost": "Dec 12 2025 09:10PM",
      "content": "Just watched a documentary on regenerative farming. Mind-blown by how much we can improve soil health globally. Must-watch for everyone. Watch it now: https://docuhub.com/regenerative-farming-doc",
      "iframe": "",
      "video": "",
      "image": "",
      "likes": 1150,
      "liked": true,
      "topic": "Environment"
    },
    {
      "name": "Sam W",
      "username": "SketchArtist",
      "datePost": "Dec 12 2025 09:05PM",
      "content": "Working on a commission piece with charcoal. It's messy, but the depth you can get is unmatched. Will post the finished result tomorrow! Tips for charcoal art: https://artsupply.com/charcoal-guide",
      "iframe": "",
      "video": "",
      "image": "",
      "likes": 812,
      "liked": false,
      "topic": "Art"
    },
    {
      "name": "Chloe B",
      "username": "GreenThumbGal",
      "datePost": "Dec 12 2025 09:00PM",
      "content": "The morning sun hitting my succulents is just perfect. Little moments of quiet beauty are the best. ☀️",
      "iframe": "",
      "video": "",
      "image": "https://cdn.assets.com/greenthumbgal/succulent_photo2.jpg",
      "likes": 640,
      "liked": true,
      "topic": "Gardening"
    },
    {
      "name": "Nate T",
      "username": "HistoryHound",
      "datePost": "Dec 12 2025 08:55PM",
      "content": "Fun historical fact: The shortest war in history lasted only 38 to 45 minutes. Imagine calling in sick to war! 😂 Read the details: https://historicfacts.org/anglo-zanzibar-war-38-minutes",
      "iframe": "",
      "video": "",
      "image": "",
      "likes": 1502,
      "liked": true,
      "topic": "History"
    },
    {
      "name": "Eva P",
      "username": "ProductivityPro",
      "datePost": "Dec 12 2025 08:50PM",
      "content": "If you're stuck, try the Pomodoro Technique. 25 minutes of work, 5 minutes break. It cuts through procrastination like butter. #WorkHacks Guide to Pomodoro: https://productivity.com/pomodoro-technique-guide",
      "iframe": "",
      "video": "",
      "image": "",
      "likes": 1055,
      "liked": false,
      "topic": "Productivity"
    },
    {
      "name": "Jack M",
      "username": "CityExplorer",
      "datePost": "Dec 12 2025 08:45PM",
      "content": "Found the absolute best hole-in-the-wall taco truck downtown. The Al Pastor is next-level. Always trust local recs. 🌮 Find their location on MapApp: https://mapapp.com/taco-truck-location/al-pastor-king",
      "iframe": "",
      "video": "",
      "image": "https://cdn.assets.com/cityexplorer/taco_truck_photo.jpg",
      "likes": 2300,
      "liked": true,
      "topic": "Food"
    },
    {
      "name": "Tina R",
      "username": "PetLoverTR",
      "datePost": "Dec 12 2025 08:40PM",
      "content": "My dog just tried to 'bury' a piece of cheese in the carpet. He's cute, but he's not the brightest. Send cleaning tips! 🐶🧀 Best pet stain removal: https://petsafety.org/cleaning-cheese-stains",
      "iframe": "",
      "video": "",
      "image": "https://cdn.assets.com/petlovertr/dog_photo.jpg",
      "likes": 1870,
      "liked": true,
      "topic": "Pets"
    },
    {
      "name": "Wesley H",
      "username": "FitnessFanatic",
      "datePost": "Dec 12 2025 08:35PM",
      "content": "Hit a new personal best on my deadlift today! Consistency truly is the key. Celebrate the small wins! 💪 Check out my form analysis: https://www.youtube.com/embed/deadlift-form-check-vlog",
      "iframe": "",
      "video": "https://cdn.assets.com/fitnessfanatic/deadlift_clip.mp4",
      "image": "",
      "likes": 750,
      "liked": false,
      "topic": "Fitness"
    },
    {
      "name": "Priya S",
      "username": "DigitalDesigner",
      "datePost": "Dec 12 2025 08:30PM",
      "content": "Diving into learning Blender 3D modeling tonight. It feels like trying to learn a new language, but I'm loving the process. Free Blender tutorials: https://blenderguru.com/free-tutorials",
      "iframe": "",
      "video": "",
      "image": "",
      "likes": 405,
      "liked": false,
      "topic": "Design"
    },
    {
      "name": "George L",
      "username": "TravelerGL",
      "datePost": "Dec 12 2025 08:25PM",
      "content": "Best travel advice I ever got: always pack a universal adaptor and an open mind. Ready for the next adventure! 🌍 Must-have travel gadgets: https://travelgear.com/universal-adaptors",
      "iframe": "",
      "video": "",
      "image": "",
      "likes": 1350,
      "liked": true,
      "topic": "Travel"
    },
    {
      "name": "Mia V",
      "username": "TheFashionista",
      "datePost": "Dec 12 2025 08:20PM",
      "content": "Color of the season? Definitely deep emerald green. It looks amazing on everyone. Time to refresh the wardrobe. Shop the trend: https://fashiontrends.com/emerald-green-collection",
      "iframe": "",
      "video": "",
      "image": "",
      "likes": 995,
      "liked": false,
      "topic": "Fashion"
    },
    {
      "name": "Ben F",
      "username": "MovieBuffBen",
      "datePost": "Dec 12 2025 08:15PM",
      "content": "Just watched a truly terrible B-movie, and honestly, it was kind of perfect. Sometimes bad is good. Anyone else enjoy cinematic trash? Join the B-Movie subreddit: https://reddit.com/r/badmovies",
      "iframe": "",
      "video": "",
      "image": "",
      "likes": 510,
      "liked": true,
      "topic": "Entertainment"
    },
    {
      "name": "Elias K",
      "username": "RetroGrade",
      "datePost": "Dec 12 2025 08:10PM",
      "content": "Found my old Discman today. The satisfying *click* when you close the lid... pure 90s gold. Do people even know what CDs are anymore? Buy a refurbished Discman: https://retroelectronics.com/discman-90s-classic",
      "iframe": "",
      "video": "",
      "image": "",
      "likes": 790,
      "liked": true,
      "topic": "Nostalgia"
    },
    {
      "name": "Laura D",
      "username": "RecipeRider",
      "datePost": "Dec 12 2025 08:05PM",
      "content": "Meal prepping hack: make one massive batch of rice or quinoa on Sunday. It saves so much time during the week! Quinoa vs. Rice debate: https://nutritionfacts.org/quinoa-vs-rice-meal-prep",
      "iframe": "",
      "video": "",
      "image": "",
      "likes": 1420,
      "liked": false,
      "topic": "Food"
    },
    {
      "name": "Alex R",
      "username": "CodeConnoisseur",
      "datePost": "Dec 12 2025 08:00PM",
      "content": "Started using Dark Mode everywhere. My eyes thank me. Why did we ever use bright white screens? The 90s were dark for a reason, people. How to enable Dark Mode in all apps: https://techblog.com/dark-mode-guide",
      "iframe": "",
      "video": "",
      "image": "",
      "likes": 2011,
      "liked": true,
      "topic": "Tech"
    },
    {
      "name": "Jess W",
      "username": "FinancialGworl",
      "datePost": "Dec 12 2025 07:55PM",
      "content": "Pro-tip for student loans: pay more than the minimum *whenever* you can. Even small extra payments make a difference over time. Use this calculator: https://loanfree.org/student-loan-accelerator",
      "iframe": "",
      "video": "",
      "image": "",
      "likes": 900,
      "liked": true,
      "topic": "Money"
    },
    {
      "name": "Noah T",
      "username": "SlayTheDay",
      "datePost": "Dec 12 2025 07:50PM",
      "content": "A moment of silence for the perfect winged eyeliner I achieved this morning. It will never happen again. Too powerful. 😫 Watch the tutorial I followed: https://www.youtube.com/embed/winged-liner-tutorial",
      "iframe": "https://www.youtube.com/embed/winged-liner-tutorial",
      "video": "",
      "image": "https://cdn.assets.com/slaytheday/eyeliner_photo.jpg",
      "likes": 1600,
      "liked": false,
      "topic": "Aesthetics"
    },
    {
      "name": "Maya L",
      "username": "JustCantEven",
      "datePost": "Dec 12 2025 07:45PM",
      "content": "Is it just me, or does hitting 'reply all' when you meant to hit 'reply' trigger a full-body fight-or-flight response? Every. Single. Time. Avoiding email mistakes: https://worketiquette.com/reply-all-horror",
      "iframe": "",
      "video": "",
      "image": "",
      "likes": 1220,
      "liked": true,
      "topic": "Venting"
    },
    {
      "name": "Hannah S",
      "username": "BookWormHS",
      "datePost": "Dec 12 2025 07:40PM",
      "content": "Currently trying to decide which classic novel to tackle next. Dickens? Tolstoy? Send me your longest, most intimidating recommendation! List of intimidating classics: https://literarylife.org/longest-novels",
      "iframe": "",
      "video": "",
      "image": "",
      "likes": 850,
      "liked": false,
      "topic": "Books"
    },
    {
      "name": "Ryan Z",
      "username": "TheGamerHub",
      "datePost": "Dec 12 2025 07:35PM",
      "content": "Just unlocked the hardest achievement in that new RPG. The feeling of pure, unadulterated satisfaction is unmatched. Worth the grind. Guide to the achievement: https://rpgfanatics.com/achievement-guide/unyielding-spirit",
      "iframe": "",
      "video": "",
      "image": "",
      "likes": 955,
      "liked": true,
      "topic": "Gaming"
    },
    {
      "name": "Sarah M",
      "username": "PettyPigeon",
      "datePost": "Dec 12 2025 07:30PM",
      "content": "Why is it that the one sock I need is always in the absolute last place I look? It's a conspiracy, I swear. Scientific explanation for lost socks: https://randomscience.org/sock-mystery-theory",
      "iframe": "",
      "video": "",
      "image": "",
      "likes": 1100,
      "liked": false,
      "topic": "Random"
    },
    {
      "name": "Kevin J",
      "username": "CryptoKingKJ",
      "datePost": "Dec 12 2025 07:25PM",
      "content": "Watching the market charts while simultaneously trying to cook dinner is a wild combination of stress and hope. Wish me luck. 🤞 Live market tracker: https://coincharts.io/live-tracker",
      "iframe": "",
      "video": "",
      "image": "",
      "likes": 615,
      "liked": true,
      "topic": "Finance"
    },
    {
      "name": "Daniel P",
      "username": "ScienceGuyDP",
      "datePost": "Dec 12 2025 07:20PM",
      "content": "Just ran an experiment that failed spectacularly. That's science! Learning more from the errors than the successes. Back to the drawing board. Read about the value of failure in research: https://scientificjournal.com/failure-as-data",
      "iframe": "",
      "video": "",
      "image": "",
      "likes": 1450,
      "liked": false,
      "topic": "Science"
    },
    {
      "name": "Zoe C",
      "username": "MindfulZen",
      "datePost": "Dec 12 2025 07:15PM",
      "content": "If you're feeling overwhelmed, try the 5-4-3-2-1 grounding technique. Focus on five things you see, four you feel, three you hear... it helps. Full grounding guide: https://anxietyhelp.org/54321-grounding",
      "iframe": "",
      "video": "",
      "image": "",
      "likes": 1020,
      "liked": true,
      "topic": "Wellness"
    },
    {
      "name": "Marcus E",
      "username": "DIYKingME",
      "datePost": "Dec 12 2025 07:10PM",
      "content": "Started stripping paint off an old wooden chair. This is definitely a two-weekend project, not a two-hour project. Patience is key! Best methods for stripping old paint: https://homeimprovement.com/paint-stripping-tutorial",
      "iframe": "",
      "video": "",
      "image": "",
      "likes": 500,
      "liked": false,
      "topic": "DIY"
    },
    {
      "name": "Kelly A",
      "username": "CoffeeQueen",
      "datePost": "Dec 12 2025 07:05PM",
      "content": "Just invented a new iced coffee combination: Lavender syrup, a splash of oat milk, and a double shot. It tastes like a chill Friday night. Recipe for homemade lavender syrup: https://coffeeculture.com/lavender-syrup-recipe",
      "iframe": "",
      "video": "",
      "image": "",
      "likes": 1780,
      "liked": true,
      "topic": "Food"
    },
    {
      "name": "Liam B",
      "username": "TheMusician",
      "datePost": "Dec 12 2025 07:00PM",
      "content": "Practicing improvisation tonight. Sometimes the best musical moments are the ones you didn't plan at all. Watch the full jam session:",
      "iframe": "https://www.youtube.com/embed/liam-improv-session",
      "video": "https://cdn.assets.com/themusician/improv_clip.mp4",
      "image": "",
      "likes": 440,
      "liked": true,
      "topic": "Music"
    },
    {
      "name": "Grace F",
      "username": "WorldCitizenGF",
      "datePost": "Dec 12 2025 06:55PM",
      "content": "Participated in a community clean-up today. Felt good giving back to the planet, even in a small way. Every little bit counts! Find a local clean-up event: https://cleanup-events.org/find-near-you",
      "iframe": "",
      "video": "",
      "image": "",
      "likes": 985,
      "liked": false,
      "topic": "Environment"
    },
    {
      "name": "Sam W",
      "username": "SketchArtist",
      "datePost": "Dec 12 2025 06:50PM",
      "content": "Playing with perspective today. It's the little vanishing points that make or break a drawing. The struggle is real, but rewarding. Guide to one-point perspective: https://drawingfundamentals.com/one-point-perspective",
      "iframe": "",
      "video": "",
      "image": "",
      "likes": 730,
      "liked": true,
      "topic": "Art"
    },
    {
      "name": "Chloe B",
      "username": "GreenThumbGal",
      "datePost": "Dec 12 2025 06:45PM",
      "content": "Just potted a baby spider plant! They are so resilient and easy to propagate. Happy 50th post, everyone! Celebrating with my green babies. 🌱🎉 Learn how to propagate: https://planttips.org/spider-plant-propagation",
      "iframe": "",
      "video": "",
      "image": "",
      "likes": 915,
      "liked": false,
      "topic": "Gardening"
    },
    {
      "name": "Maya L",
      "username": "JustCantEven",
      "datePost": "Dec 12 2025 10:25PM",
      "content": "My 'I'm just gonna run a quick errand' turned into a 3-hour saga. Why is the universe testing me on a Friday? I just wanted milk. Send snacks.",
      "iframe": "",
      "video": "",
      "image": "",
      "likes": 711,
      "liked": false,
      "topic": "Venting"
    },
    {
      "name": "Noah T",
      "username": "SlayTheDay",
      "datePost": "Dec 12 2025 10:23PM",
      "content": "Lowkey obsessed with this new color palette I found. The neutrals are giving main character energy. 🎨✨",
      "iframe": "",
      "video": "",
      "image": "",
      "likes": 1950,
      "liked": true,
      "topic": "Aesthetics"
    },
    {
      "name": "Jess W",
      "username": "FinancialGworl",
      "datePost": "Dec 12 2025 10:20PM",
      "content": "The way my bank account looks at me after I remember I have bills due. It's giving silence and disappointment. We'll bounce back, bestie.",
      "iframe": "",
      "video": "",
      "image": "",
      "likes": 602,
      "liked": false,
      "topic": "Money"
    },
    {
      "name": "Elias K",
      "username": "RetroGrade",
      "datePost": "Dec 12 2025 10:18PM",
      "content": "Storytime: Did anyone else think those tiny, weirdly textured plastic rings from the 2000s were peak jewelry? I was a menace, honestly.",
      "iframe": "",
      "video": "",
      "image": "",
      "likes": 477,
      "liked": true,
      "topic": "Nostalgia"
    },
    {
      "name": "Sarah M",
      "username": "PettyPigeon",
      "datePost": "Dec 12 2025 10:15PM",
      "content": "I think the opposite of adulting is just buying yourself that random plushie you saw in the clearance bin. Self-care, look it up.",
      "iframe": "",
      "video": "",
      "image": "",
      "likes": 1401,
      "liked": false,
      "topic": "Random"
    },
    {
      "name": "Alex R",
      "username": "CodeConnoisseur",
      "datePost": "Dec 12 2025 10:12PM",
      "content": "Just spent 4 hours tracking down a bug only to realize I used '==' instead of '==='. The rubber duck is judging me hard right now. #DevLife",
      "iframe": "",
      "video": "",
      "image": "",
      "likes": 2548,
      "liked": true,
      "topic": "Tech"
    },
    {
      "name": "Chloe B",
      "username": "GreenThumbGal",
      "datePost": "Dec 12 2025 10:09PM",
      "content": "My Monstera just put out a new leaf and it's HUGE. Feeling like a proud plant parent. 🌿💚 What are your favorite low-maintenance indoor plants?",
      "iframe": "",
      "video": "",
      "image": "monstera_photo.jpg",
      "likes": 887,
      "liked": false,
      "topic": "Gardening"
    },
    {
      "name": "Ben F",
      "username": "MovieBuffBen",
      "datePost": "Dec 12 2025 10:05PM",
      "content": "Rewatching a classic and realizing all the subtle foreshadowing I missed as a kid. This film is a masterpiece. Highly recommend! (It's Jaws, btw)",
      "iframe": "",
      "video": "",
      "image": "",
      "likes": 321,
      "liked": true,
      "topic": "Entertainment"
    },
    {
      "name": "Olivia P",
      "username": "WanderLustOP",
      "datePost": "Dec 12 2025 10:02PM",
      "content": "Just booked my trip for April! Trading city views for mountain air. Time to start making the playlist. Any destination recommendations for next time?",
      "iframe": "",
      "video": "",
      "image": "",
      "likes": 1655,
      "liked": false,
      "topic": "Travel"
    },
    {
      "name": "Ethan H",
      "username": "QuietThinker",
      "datePost": "Dec 12 2025 09:58PM",
      "content": "Spent the last hour just sitting in silence and listening to the rain. Sometimes you need to let the world be loud so your own thoughts can be quiet.",
      "iframe": "",
      "video": "",
      "image": "",
      "likes": 912,
      "liked": true,
      "topic": "Reflect"
    },
    {
      "name": "Maya L",
      "username": "JustCantEven",
      "datePost": "Dec 12 2025 10:25PM",
      "content": "My 'I'm just gonna run a quick errand' turned into a 3-hour saga. Why is the universe testing me on a Friday? I just wanted milk. Send snacks.",
      "iframe": "",
      "video": "",
      "image": "",
      "likes": 711,
      "liked": false,
      "topic": "Venting"
    },
    {
      "name": "Noah T",
      "username": "SlayTheDay",
      "datePost": "Dec 12 2025 10:23PM",
      "content": "Lowkey obsessed with this new color palette I found. The neutrals are giving main character energy. 🎨✨",
      "iframe": "",
      "video": "",
      "image": "",
      "likes": 1950,
      "liked": true,
      "topic": "Aesthetics"
    },
    {
      "name": "Jess W",
      "username": "FinancialGworl",
      "datePost": "Dec 12 2025 10:20PM",
      "content": "The way my bank account looks at me after I remember I have bills due. It's giving silence and disappointment. We'll bounce back, bestie.",
      "iframe": "",
      "video": "",
      "image": "",
      "likes": 602,
      "liked": false,
      "topic": "Money"
    },
    {
      "name": "Elias K",
      "username": "RetroGrade",
      "datePost": "Dec 12 2025 10:18PM",
      "content": "Storytime: Did anyone else think those tiny, weirdly textured plastic rings from the 2000s were peak jewelry? I was a menace, honestly.",
      "iframe": "",
      "video": "",
      "image": "",
      "likes": 477,
      "liked": true,
      "topic": "Nostalgia"
    },
    {
      "name": "Sarah M",
      "username": "PettyPigeon",
      "datePost": "Dec 12 2025 10:15PM",
      "content": "I think the opposite of adulting is just buying yourself that random plushie you saw in the clearance bin. Self-care, look it up.",
      "iframe": "",
      "video": "",
      "image": "",
      "likes": 1401,
      "liked": false,
      "topic": "Random"
    },
    {
      "name": "Alex R",
      "username": "CodeConnoisseur",
      "datePost": "Dec 12 2025 10:12PM",
      "content": "Just spent 4 hours tracking down a bug only to realize I used '==' instead of '==='. The rubber duck is judging me hard right now. #DevLife",
      "iframe": "",
      "video": "",
      "image": "",
      "likes": 2548,
      "liked": true,
      "topic": "Tech"
    },
    {
      "name": "Chloe B",
      "username": "GreenThumbGal",
      "datePost": "Dec 12 2025 10:09PM",
      "content": "My Monstera just put out a new leaf and it's HUGE. Feeling like a proud plant parent. 🌿💚 What are your favorite low-maintenance indoor plants?",
      "iframe": "",
      "video": "",
      "image": "monstera_photo.jpg",
      "likes": 887,
      "liked": false,
      "topic": "Gardening"
    },
    {
      "name": "Ben F",
      "username": "MovieBuffBen",
      "datePost": "Dec 12 2025 10:05PM",
      "content": "Rewatching a classic and realizing all the subtle foreshadowing I missed as a kid. This film is a masterpiece. Highly recommend! (It's Jaws, btw)",
      "iframe": "",
      "video": "",
      "image": "",
      "likes": 321,
      "liked": true,
      "topic": "Entertainment"
    },
    {
      "name": "Olivia P",
      "username": "WanderLustOP",
      "datePost": "Dec 12 2025 10:02PM",
      "content": "Just booked my trip for April! Trading city views for mountain air. Time to start making the playlist. Any destination recommendations for next time?",
      "iframe": "",
      "video": "",
      "image": "",
      "likes": 1655,
      "liked": false,
      "topic": "Travel"
    },
    {
      "name": "Ethan H",
      "username": "QuietThinker",
      "datePost": "Dec 12 2025 09:58PM",
      "content": "Spent the last hour just sitting in silence and listening to the rain. Sometimes you need to let the world be loud so your own thoughts can be quiet.",
      "iframe": "",
      "video": "",
      "image": "",
      "likes": 912,
      "liked": true,
      "topic": "Reflect"
    },
    {
      "name": "ArchitecturalDigest",
      "username": "Design_Enthusiast",
      "datePost": "Dec 12 2025 10:00PM",
      "content": "We just published an exclusive tour of the new Hyperion Museum! The use of light and concrete is revolutionary. Watch the full video walkthrough here.",
      "iframe": "https://www.youtube.com/embed/MuseumDesignTour",
      "video": "",
      "image": "",
      "likes": 1800,
      "liked": false,
      "topic": "Architecture"
    },
    {
      "name": "GardeningGoals",
      "username": "Flora_and_Fauna",
      "datePost": "Dec 12 2025 9:30PM",
      "content": "The first bloom of my rare desert rose! It took three years of patience, but the result is stunning. Hard work pays off! 🌸",
      "iframe": "",
      "video": "",
      "image": "https://i.imgur.com/DesertRoseBloom.jpg",
      "likes": 950,
      "liked": true,
      "topic": "Gardening"
    },
    {
      "name": "GamingCentral",
      "username": "EpicLooter",
      "datePost": "Dec 12 2025 8:40PM",
      "content": "Just managed to beat the final boss on Legendary difficulty! Took 50 attempts, but here is the clip of the winning blow. Never give up!",
      "iframe": "",
      "video": "https://vimeo.com/FinalBossClip",
      "image": "",
      "likes": 3100,
      "liked": false,
      "topic": "Gaming"
    },
    {
      "name": "podk",
      "username": "podk29",
      "datePost": "Dec 13 2025 8:43PM",
      "content": "@hantic beacuse meko only saved posts that are in the server butnever the cache beacuse is outside of the server it wad never been filtered. and by deleting cache posts they can prevent posts that are violated their policy and posts are not not allowed",
      "iframe": "",
      "video": "",
      "image": "",
      "likes": 79,
      "liked": false,
      "topic": "AboutMeko"
    },
    {
      "name": "hantic",
      "username": "hantic",
      "datePost": "Dec 13 2025 8:43PM",
      "content": "Cache Posts are being Deleted? why?",
      "iframe": "",
      "video": "",
      "image": "",
      "likes": 32859,
      "liked": false,
      "topic": "AboutMeko"
    },

    {
      "name": "florenz",
      "username": "florenz",
      "datePost": "Jul 21 2023 9:17PM",
      "content": "Chess <error= Video source not found",
      "iframe": "",
      "video": "",
      "image": "",
      "likes": 853,
      "liked": false,
      "topic": "AboutMeko"
    },
    {
      "name": "florenz",
      "username": "florenz",
      "datePost": "Jul 20 2023 7:21PM",
      "content": "Hi",
      "iframe": "",
      "video": "",
      "image": "",
      "likes": 795,
      "liked": false,
      "topic": "AboutMeko"
    },
    {
      "name": "Meko",
      "username": "Meko",
      "datePost": "Jun 4 2022 4:28AM",
      "content": "Test",
      "iframe": "",
      "video": "",
      "image": "",
      "likes": 10385,
      "liked": false,
      "topic": "AboutMeko"
    },
    {
      "name": "Medalya Villaflor",
      "username": "Medalya Villaflor",
      "datePost": "Jun 1 2022 10:37PM",
      "content": "Test account",
      "iframe": "",
      "video": "",
      "image": "",
      "likes": 1624,
      "liked": false,
      "topic": "AboutMeko"
    }
  ]
